{
  "clientId": "admin-api",
  "name": "",
  "description": "",
  "rootUrl": "",
  "adminUrl": "",
  "baseUrl": "",
  "surrogateAuthRequired": false,
  "enabled": true,
  "alwaysDisplayInConsole": false,
  "clientAuthenticatorType": "client-secret",
  "secret": "03QO3OEnCTY5YYzzMlhyAUCEiN032geE",
  "redirectUris": [
    "/*"
  ],
  "webOrigins": [
    "/*"
  ],
  "notBefore": 0,
  "bearerOnly": false,
  "consentRequired": false,
  "standardFlowEnabled": true,
  "implicitFlowEnabled": false,
  "directAccessGrantsEnabled": true,
  "serviceAccountsEnabled": true,
  "publicClient": false,
  "frontchannelLogout": true,
  "protocol": "openid-connect",
  "attributes": {
    "oidc.ciba.grant.enabled": "false",
    "oauth2.device.authorization.grant.enabled": "false",
    "client.secret.creation.time": "1715234041",
    "backchannel.logout.session.required": "true",
    "backchannel.logout.revoke.offline.tokens": "false"
  },
  "authenticationFlowBindingOverrides": {},
  "fullScopeAllowed": true,
  "nodeReRegistrationTimeout": -1,
  "protocolMappers": [
    {
      "name": "Client Host",
      "protocol": "openid-connect",
      "protocolMapper": "oidc-usersessionmodel-note-mapper",
      "consentRequired": false,
      "config": {
        "user.session.note": "clientHost",
        "introspection.token.claim": "true",
        "id.token.claim": "true",
        "access.token.claim": "true",
        "claim.name": "clientHost",
        "jsonType.label": "String"
      }
    },
    {
      "name": "Client IP Address",
      "protocol": "openid-connect",
      "protocolMapper": "oidc-usersessionmodel-note-mapper",
      "consentRequired": false,
      "config": {
        "user.session.note": "clientAddress",
        "introspection.token.claim": "true",
        "id.token.claim": "true",
        "access.token.claim": "true",
        "claim.name": "clientAddress",
        "jsonType.label": "String"
      }
    },
    {
      "name": "Client ID",
      "protocol": "openid-connect",
      "protocolMapper": "oidc-usersessionmodel-note-mapper",
      "consentRequired": false,
      "config": {
        "user.session.note": "client_id",
        "introspection.token.claim": "true",
        "id.token.claim": "true",
        "access.token.claim": "true",
        "claim.name": "client_id",
        "jsonType.label": "String"
      }
    }
  ],
  "defaultClientScopes": [
    "web-origins",
    "acr",
    "roles",
    "profile",
    "email"
  ],
  "optionalClientScopes": [
    "address",
    "phone",
    "offline_access",
    "microprofile-jwt"
  ],
  "access": {
    "view": true,
    "configure": true,
    "manage": true
  }
}